MDIC3
