Metadata-Version: 2.1
Name: MDIC3
Version: 1.0.2
Summary: A Lucky Python Package
Home-page: https://github.com/LYxiaotai/MDIC3
Author: Lyxiaotai
Author-email: liuyi54894xiaotai@163.com
